<?xml version="1.0" encoding="utf-8"?>
<VectorNav_Sensor xmlns:xsd="http://www.w3.org/2001/XMLSchema" xmlns:xsi="http://www.w3.org/2001/XMLSchema-instance">
  <Model>VN-200S-CR</Model>
  <HardwareRevision>2</HardwareRevision>
  <SerialNumber>0100023293</SerialNumber>
  <FirmwareVersion>1.0.1.0.0.0</FirmwareVersion>
  <Register>
    <Id>5</Id>
    <Name>BaudRate</Name>
    <Values>921600</Values>
  </Register>
  <Register>
    <Id>6</Id>
    <Name>AsyncOutputType</Name>
    <Values>0</Values>
  </Register>
  <Register>
    <Id>75</Id>
    <Name>BinaryOutput1</Name>
    <Values>1,2,3E,0002,0600,0020,0006,0008</Values>
  </Register>
</VectorNav_Sensor>